cactus/__init__.py
cactus/browser.py
cactus/cli.py
cactus/exceptions.py
cactus/logger.py
cactus/mime.py
cactus/page.py
cactus/server.py
cactus/site.py
cactus/template_tags.py
cactus/ui.py
cactus/bootstrap/__init__.py
cactus/bootstrap/archive.py
cactus/bootstrap/package.py
cactus/compat/__init__.py
cactus/compat/page.py
cactus/compat/paths.py
cactus/config/__init__.py
cactus/config/fallback.py
cactus/config/file.py
cactus/config/router.py
cactus/contrib/__init__.py
cactus/contrib/external/__init__.py
cactus/contrib/external/closure.py
cactus/contrib/external/sass.py
cactus/contrib/external/yui.py
cactus/deployment/__init__.py
cactus/deployment/auth.py
cactus/deployment/engine.py
cactus/deployment/exception.py
cactus/deployment/file.py
cactus/deployment/cloudfiles/__init__.py
cactus/deployment/cloudfiles/auth.py
cactus/deployment/cloudfiles/engine.py
cactus/deployment/cloudfiles/file.py
cactus/deployment/gcs/__init__.py
cactus/deployment/gcs/auth.py
cactus/deployment/gcs/engine.py
cactus/deployment/gcs/file.py
cactus/deployment/s3/__init__.py
cactus/deployment/s3/auth.py
cactus/deployment/s3/domain.py
cactus/deployment/s3/engine.py
cactus/deployment/s3/file.py
cactus/i18n/__init__.py
cactus/i18n/commands.py
cactus/listener/__init__.py
cactus/listener/mac.py
cactus/listener/polling.py
cactus/plugin/__init__.py
cactus/plugin/defaults.py
cactus/plugin/loader.py
cactus/plugin/manager.py
cactus/plugin/builtin/__init__.py
cactus/plugin/builtin/cache.py
cactus/plugin/builtin/context.py
cactus/plugin/builtin/ignore.py
cactus/plugin/builtin/page_context.py
cactus/skeleton/config.json
cactus/skeleton/locale/README.md
cactus/skeleton/pages/about.html
cactus/skeleton/pages/contact.html
cactus/skeleton/pages/error.html
cactus/skeleton/pages/index.html
cactus/skeleton/pages/robots.txt
cactus/skeleton/pages/sitemap.xml
cactus/skeleton/plugins/__init__.py
cactus/skeleton/plugins/blog.disabled.py
Cactus-3.3.2.dist-info/DESCRIPTION.rst
Cactus-3.3.2.dist-info/entry_points.txt
Cactus-3.3.2.dist-info/METADATA
Cactus-3.3.2.dist-info/metadata.json
Cactus-3.3.2.dist-info/pbr.json
Cactus-3.3.2.dist-info/RECORD
Cactus-3.3.2.dist-info/top_level.txt
Cactus-3.3.2.dist-info/WHEEL
