Metadata-Version: 2.0
Name: Cactus
Version: 3.3.2
Summary: Static site generation and deployment.
Home-page: http://github.com/koenbok/Cactus
Author: Koen Bok
Author-email: koen@madebysofa.com
License: BSD
Platform: UNKNOWN
Classifier: Development Status :: 4 - Beta
Classifier: Environment :: Console
Classifier: Intended Audience :: Developers
Classifier: License :: OSI Approved :: BSD License
Classifier: Natural Language :: English
Classifier: Operating System :: OS Independent
Classifier: Programming Language :: Python :: 2
Classifier: Programming Language :: Python :: 2.6
Classifier: Programming Language :: Python :: 2.7
Classifier: Programming Language :: Python :: 3
Classifier: Programming Language :: Python :: 3.4
Classifier: Topic :: Internet :: WWW/HTTP
Requires-Dist: Django (>=1.6,<1.7)
Requires-Dist: django-markwhat (>=1.4,<2)
Requires-Dist: markdown2
Requires-Dist: argparse
Requires-Dist: keyring
Requires-Dist: boto (>=2.4.1)
Requires-Dist: tornado (>=3.2)
Requires-Dist: colorlog
Requires-Dist: colorama
Requires-Dist: six (>=1.9.0)
Provides-Extra: Cloud Files Deployment
Requires-Dist: pyrax; extra == 'Cloud Files Deployment'
Provides-Extra: GCS Deployment
Requires-Dist: google-api-python-client; extra == 'GCS Deployment'
Provides-Extra: Mac Native FSEvents
Requires-Dist: macfsevents; extra == 'Mac Native FSEvents'
